Metadata-Version: 1.1
Name: palindromus
Version: 1.0.3
Summary: Package palindromus helps you to check that any string, word or text are palindrome
Home-page: https://github.com/vowatchka/palindromus
Author: Vladimir Saltykov
Author-email: vowatchka@mail.ru
License: MIT
Keywords: palindromus palindrome check string word phrase text multiline superpalindrome
Platform: UNKNOWN
Classifier: Development Status :: 5 - Production/Stable
Classifier: Intended Audience :: Developers
Classifier: License :: OSI Approved :: MIT License
Classifier: Operating System :: OS Independent
Classifier: Programming Language :: Python :: 3
Classifier: Programming Language :: Python :: 3.5
Classifier: Programming Language :: Python :: 3.6
Classifier: Programming Language :: Python :: 3.7
Classifier: Topic :: Software Development :: Libraries :: Python Modules
Classifier: Topic :: Utilities
